backendrasp/ShynaBroadcastMessageDecision.py
backendrasp/ShynaClearHistory.py
backendrasp/ShynaFaceRecognition.py
backendrasp/ShynaGetQuotes.py
backendrasp/ShynaGreetings.py
backendrasp/ShynaIs.py
backendrasp/ShynaJokes.py
backendrasp/ShynaMasterNotify.py
backendrasp/ShynaSpeak.py
backendrasp/ShynaStatusCheck.py
backendrasp/ShynaTelegramBot.py
backendrasp/ShynaTwelveAMTask.py
backendrasp/ShynaWeather.py
backendrasp/SpeechNotify.py
backendrasp/UpdateDistance.py
backendrasp/UpdateWeather.py
backendrasp/__init__.py
backendrasp-0.0.16.dist-info/LICENSE
backendrasp-0.0.16.dist-info/METADATA
backendrasp-0.0.16.dist-info/WHEEL
backendrasp-0.0.16.dist-info/top_level.txt
backendrasp-0.0.16.dist-info/RECORD
