Metadata-Version: 2.1
Name: backendrasp
Version: 0.0.16
Summary: Shyna Backend Functionality Package For Rasp
Author: Shivam Sharma
Author-email: shivamsharma1913@gmail.com
License-File: LICENSE
Requires-Dist: setuptools
Requires-Dist: wheel
Requires-Dist: ShynaTime
Requires-Dist: ShynaDatabase
Requires-Dist: nltk
Requires-Dist: requests
Requires-Dist: face-recognition
Requires-Dist: googlesearch-python
Requires-Dist: wikipedia
Requires-Dist: IMDbPY
Requires-Dist: wget
Requires-Dist: telegram
Requires-Dist: feedparser
Requires-Dist: google-speech
Requires-Dist: haversine
